jutility/__init__.py
jutility/cli/__init__.py
jutility/cli/arg.py
jutility/cli/group.py
jutility/cli/object_arg.py
jutility/cli/object_choice.py
jutility/cli/parent.py
jutility/cli/parsed_args.py
jutility/cli/parser.py
jutility/cli/unknown.py
jutility/cli/verbose.py
jutility/cli/subcmd/group.py
jutility/cli/subcmd/no_group.py
jutility/cli/subcmd/parent.py
jutility/cli/subcmd/subcommand.py
jutility/plotting/__init__.py
jutility/plotting/colour_picker.py
jutility/plotting/gif.py
jutility/plotting/latex.py
jutility/plotting/multiplot.py
jutility/plotting/plot.py
jutility/plotting/plottable.py
jutility/plotting/properties.py
jutility/plotting/show.py
jutility/plotting/temp_axis.py
jutility/plotting/time_sweep.py
jutility/plotting/figure/fig_props.py
jutility/plotting/figure/grid_props.py
jutility/plotting/figure/legend.py
jutility/plotting/noisy/bounds.py
jutility/plotting/noisy/curve.py
jutility/plotting/noisy/curve_sweep.py
jutility/plotting/noisy/data.py
jutility/plotting/noisy/sweep.py
jutility/plotting/subplot/axis_props.py
jutility/plotting/subplot/colour_bar.py
jutility/plotting/subplot/empty.py
jutility/plotting/subplot/legend.py
jutility/plotting/subplot/subplot.py
jutility/util/__init__.py
jutility/util/context_util.py
jutility/util/dict_util.py
jutility/util/img_util.py
jutility/util/interval.py
jutility/util/iter_util.py
jutility/util/md_util.py
jutility/util/np_util.py
jutility/util/print_util.py
jutility/util/save_load.py
jutility/util/str_fmt.py
jutility/util/str_util.py
jutility/util/sys_util.py
jutility/util/test_util.py
jutility/util/time_util.py
jutility/util/units.py
jutility/util/table/column.py
jutility/util/table/func_list.py
jutility/util/table/table.py
jutility-0.0.29.dist-info/licenses/LICENSE
jutility-0.0.29.dist-info/METADATA
jutility-0.0.29.dist-info/WHEEL
jutility-0.0.29.dist-info/top_level.txt
jutility-0.0.29.dist-info/RECORD
