Metadata-Version: 2.4
Name: jutility
Version: 0.0.29
Summary: A Judicious collection of Python Utilities (including CLI configuration, plotting, and tables) and component of the JUML framework.
Author: Jake Levi
Author-email: jakelevi@hotmail.co.uk
License: MIT License
Project-URL: Homepage, https://github.com/jakelevi1996/jutility
Project-URL: Documentation, https://github.com/jakelevi1996/jutility
Project-URL: Repository, https://github.com/jakelevi1996/jutility
Requires-Python: >=3.10
License-File: LICENSE
Requires-Dist: matplotlib>=3.9.2
Requires-Dist: numpy>=1.26.3
Requires-Dist: pillow>=10.2.0
Requires-Dist: ipython>=7.34.0
Dynamic: license-file
